{"meta":{"status":200,"msg":"OK"},"response":{"blog":{"title":"youhavetostartsomewhere","name":"youhavetostartsomewhere","posts":44,"url":"http:\/\/youhavetostartsomewhere.tumblr.com\/","updated":1399244267,"description":"\u003Cbr\u003E\n\u00bbThe loss of these tastes is a loss of happiness, and may possibly be injurious to the intellect, and more probably to the moral character, by enfeebling the emotional part of our nature.\u00ab\n\u003Cbr\u003E\u003Cbr\u003E\u003Cfont size=2\u003E\u003Ca STYLE=\u0022text-decoration:none\u0022 href=\u0022\/ask\u0022\u003E\u221e\u003C\/a\u003E\u003C\/font\u003E\u003Cbr\u003E\u003Cbr\u003E\u003Ca STYLE=\u0022text-decoration:none\u0022 href=\u0022http:\/\/studio.tilensepic.com\u0022\u003EFree art by Tilen Sepic\u003C\/a\u003E","ask":true,"ask_page_title":"Ask.","ask_anon":false,"is_nsfw":false,"share_likes":false}}}
